filter_event_sink/__init__.py
filter_event_sink/cloudevents.py
filter_event_sink/config.py
filter_event_sink/filter.py
filter_event_sink/thread.py
filter_event_sink-1.1.2.dist-info/licenses/LICENSE
filter_event_sink-1.1.2.dist-info/METADATA
filter_event_sink-1.1.2.dist-info/WHEEL
filter_event_sink-1.1.2.dist-info/top_level.txt
filter_event_sink-1.1.2.dist-info/RECORD
