Metadata-Version: 2.4
Name: filter_event_sink
Version: 1.1.2
License-Expression: Apache-2.0
Classifier: Programming Language :: Python :: 3
Classifier: Programming Language :: Python :: 3.10
Classifier: Programming Language :: Python :: 3.11
Classifier: Programming Language :: Python :: 3.12
Classifier: Programming Language :: Python :: 3.13
Requires-Python: <3.14,>=3.10
License-File: LICENSE
Requires-Dist: openfilter[all]==0.1.20
Requires-Dist: requests==2.32.5
Requires-Dist: urllib3==2.6.3
Provides-Extra: dev
Requires-Dist: build==1.4.0; extra == "dev"
Requires-Dist: setuptools==80.10.1; extra == "dev"
Requires-Dist: twine==6.2.0; extra == "dev"
Requires-Dist: wheel==0.45.1; extra == "dev"
Requires-Dist: black==26.1.0; extra == "dev"
Requires-Dist: isort==7.0.0; extra == "dev"
Requires-Dist: flake8==7.3.0; extra == "dev"
Requires-Dist: pytest==9.0.2; extra == "dev"
Requires-Dist: pytest-cov==7.0.0; extra == "dev"
Requires-Dist: pytest-mock==3.15.1; extra == "dev"
Requires-Dist: responses==0.25.8; extra == "dev"
Dynamic: license-file
